eos/__init__.py
eos/compress.py
eos/git.py
eos/make_fancy_output_dir.py
eos/makedirs.py
eos/measure.py
eos/pycompat.py
eos/run_many.py
eos/time_str.py
eos/which.py
eos/apps/__init__.py
eos/apps/run_many.py
extendedos-0.1.7.dist-info/LICENSE
extendedos-0.1.7.dist-info/METADATA
extendedos-0.1.7.dist-info/WHEEL
extendedos-0.1.7.dist-info/entry_points.txt
extendedos-0.1.7.dist-info/top_level.txt
extendedos-0.1.7.dist-info/RECORD
